wttrpy/__init__.py
wttrpy-1.0.3.dist-info/LICENSE
wttrpy-1.0.3.dist-info/METADATA
wttrpy-1.0.3.dist-info/WHEEL
wttrpy-1.0.3.dist-info/top_level.txt
wttrpy-1.0.3.dist-info/RECORD
