Metadata-Version: 2.1
Name: wttrpy
Version: 1.0.3
Summary: A little thing on Python that shows you forecast using wttr.in
Home-page: https://github.com/hasha2982/wttr.py/
Author: Denisov Artem
Author-email: hashadev@yandex.ru
License: UNKNOWN
Project-URL: Documentation, https://wttrpy.rtfd.io/
Project-URL: Source Code, https://github.com/hasha2982/wttr.py/
Project-URL: Issues, https://github.com/hasha2982/wttr.py/issues/
Platform: UNKNOWN
Classifier: Programming Language :: Python :: 3.5
Classifier: Programming Language :: Python :: 3.6
Classifier: Programming Language :: Python :: 3.7
Classifier: Programming Language :: Python :: 3.8
Classifier: License :: OSI Approved :: MIT License
Classifier: Operating System :: OS Independent
Requires-Python: >=3.5
Requires-Dist: requests (<3,>=2)
